pyplasma/__init__.py
pyplasma/backend.py
pyplasma/boundaries.py
pyplasma/field_ionization.py
pyplasma/impact_ionization.py
pyplasma/laser.py
pyplasma/material.py
pyplasma/misc.py
pyplasma/observers.py
pyplasma/simulation.py
pyplasma-0.3.2.dist-info/METADATA
pyplasma-0.3.2.dist-info/WHEEL
pyplasma-0.3.2.dist-info/top_level.txt
pyplasma-0.3.2.dist-info/RECORD
