Metadata-Version: 2.1
Name: pyplasma
Version: 0.3.2
Summary: Python module for plasma formation modelling.
Home-page: https://github.com/jldez/pyplasma
Author: Jean-Luc Déziel
Author-email: jean-luc.deziel.1@ulaval.ca
License: UNKNOWN
Platform: UNKNOWN
Requires-Dist: numpy
Requires-Dist: matplotlib
Requires-Dist: scipy
Requires-Dist: tqdm
